Banz_i18n_codegenerator/__init__.py
Banz_i18n_codegenerator/generator.py
banz_i18n_codegenerator-1.1.0.dist-info/METADATA
banz_i18n_codegenerator-1.1.0.dist-info/WHEEL
banz_i18n_codegenerator-1.1.0.dist-info/entry_points.txt
banz_i18n_codegenerator-1.1.0.dist-info/licenses/LICENSE
banz_i18n_codegenerator-1.1.0.dist-info/RECORD
