Metadata-Version: 2.4
Name: Banz_i18n_codegenerator
Version: 1.1.0
Summary: Package to generate java constants for provided i18n.properties files.
Author-Email: Sebastian Banz <sebanzian@gmail.com>
License-Expression: MIT
License-File: LICENSE
Classifier: Programming Language :: Python :: 3
Classifier: Operating System :: OS Independent
Project-URL: Homepage, https://github.com/derbanz
Requires-Python: >=3.9
